_pylibCZIrw.cpython-312-darwin.so
pylibCZIrw/__init__.py
pylibCZIrw/czi.py
pylibczirw-5.1.1.dist-info/RECORD
pylibczirw-5.1.1.dist-info/WHEEL
pylibczirw-5.1.1.dist-info/top_level.txt
pylibczirw-5.1.1.dist-info/METADATA
pylibczirw-5.1.1.dist-info/licenses/COPYING.LESSER
pylibczirw-5.1.1.dist-info/licenses/NOTICE.txt
pylibczirw-5.1.1.dist-info/licenses/COPYING
