Metadata-Version: 2.4
Name: pylibCZIrw
Version: 5.1.1
Summary: A python wrapper around the libCZI C++ library with reading and writing functionality.
Author: Sebastian Soyer
Author-email: sebastian.soyer@zeiss.com
Keywords: czi,imaging
Classifier: Development Status :: 5 - Production/Stable
Classifier: Topic :: Scientific/Engineering :: Image Processing
Classifier: Programming Language :: Python :: 3.9
Classifier: Programming Language :: Python :: 3.10
Classifier: Programming Language :: Python :: 3.11
Classifier: Programming Language :: Python :: 3.12
Classifier: Programming Language :: Python :: 3.13
Classifier: License :: OSI Approved :: GNU Lesser General Public License v3 (LGPLv3)
Classifier: Operating System :: Microsoft :: Windows
Classifier: Operating System :: Unix
Classifier: Operating System :: MacOS
Requires-Python: >=3.9,<3.14
License-File: COPYING
License-File: COPYING.LESSER
License-File: NOTICE.txt
Requires-Dist: numpy
Requires-Dist: cmake
Requires-Dist: xmltodict
Requires-Dist: validators
Requires-Dist: packaging
Dynamic: author
Dynamic: author-email
Dynamic: classifier
Dynamic: description
Dynamic: description-content-type
Dynamic: keywords
Dynamic: license-file
Dynamic: requires-dist
Dynamic: requires-python
Dynamic: summary
